aimanagertoolkit/__init__.py
aimanagertoolkit/__version__.py
aimanagertoolkit/log.py
aimanagertoolkit/messages.py
aimanagertoolkit/toolbox.py
aimanagertoolkit/ai/__init__.py
aimanagertoolkit/ai/azure_ai.py
aimanagertoolkit/ai/openai_ai.py
aimanagertoolkit-0.1.12.dist-info/LICENSE
aimanagertoolkit-0.1.12.dist-info/METADATA
aimanagertoolkit-0.1.12.dist-info/WHEEL
aimanagertoolkit-0.1.12.dist-info/top_level.txt
aimanagertoolkit-0.1.12.dist-info/RECORD
