Metadata-Version: 2.1
Name: aimanagertoolkit
Version: 0.1.12
Summary: A toolkit for working with OpenAI and Azure OpenAI API
Home-page: https://github.com/Inostroza-Wingsoft/AiManagerToolkit
Author: Gustavo Inostroza
Author-email: gusinostrozar@gmail.com
Classifier: Programming Language :: Python :: 3
Classifier: License :: OSI Approved :: MIT License
Classifier: Operating System :: OS Independent
Requires-Python: >=3.7
License-File: LICENSE
Requires-Dist: openai==1.57.1
Requires-Dist: pydantic==2.10.3
Requires-Dist: python-dotenv==1.0.1
Requires-Dist: numpy==2.2.0
Requires-Dist: aiofiles==24.1.0
